pco/win_x64/etc_xcite.dll
pco/win_x64/pco_conv.dll
pco/win_x64/pco_fasc.dll
pco/win_x64/pco_fb16.dll
pco/win_x64/pco_fbmp.dll
pco/win_x64/pco_fdcm.dll
pco/win_x64/pco_ffts.dll
pco/win_x64/pco_file.dll
pco/win_x64/pco_fjp2.dll
pco/win_x64/pco_fjpg.dll
pco/win_x64/pco_fpfm.dll
pco/win_x64/pco_fpgm.dll
pco/win_x64/pco_fpng.dll
pco/win_x64/pco_fppm.dll
pco/win_x64/pco_ftif.dll
pco/win_x64/pco_recorder.dll
pco/win_x64/sc2_cam.dll
pco/win_x64/sc2_cl_me4.dll
pco/win_x64/sc2_clhs.dll
pco/win_x64/sc2_genicam.dll
pco/win_x64/sc2_gige.dll
pco/win_x64/genicam/GCBase_MD_VC141_v3_3.dll
pco/win_x64/genicam/GenApi_MD_VC141_v3_3.dll
pco/win_x64/genicam/Log_MD_VC141_v3_3.dll
pco/win_x64/genicam/MathParser_MD_VC141_v3_3.dll
pco/win_x64/genicam/NodeMapData_MD_VC141_v3_3.dll
pco/win_x64/genicam/XmlParser_MD_VC141_v3_3.dll
pco-2.5.0.data/purelib/pco/LICENSE.txt
pco-2.5.0.data/purelib/pco/__init__.py
pco-2.5.0.data/purelib/pco/camera.py
pco-2.5.0.data/purelib/pco/camera_exception.py
pco-2.5.0.data/purelib/pco/convert.py
pco-2.5.0.data/purelib/pco/defs.py
pco-2.5.0.data/purelib/pco/flim.py
pco-2.5.0.data/purelib/pco/license.pdf
pco-2.5.0.data/purelib/pco/license_3rdParty.pdf
pco-2.5.0.data/purelib/pco/loader.py
pco-2.5.0.data/purelib/pco/logging.py
pco-2.5.0.data/purelib/pco/recorder.py
pco-2.5.0.data/purelib/pco/sdk.py
pco-2.5.0.data/purelib/pco/xcite.py
pco-2.5.0.dist-info/licenses/LICENSE.txt
pco-2.5.0.dist-info/licenses/license.pdf
pco-2.5.0.dist-info/licenses/license_3rdParty.pdf
pco-2.5.0.dist-info/METADATA
pco-2.5.0.dist-info/WHEEL
pco-2.5.0.dist-info/top_level.txt
pco-2.5.0.dist-info/RECORD
